README.md
setup.py
phyloinfer/Loglikelihood.py
phyloinfer/Logposterior.py
phyloinfer/Logprior.py
phyloinfer/__init__.py
phyloinfer/branchManipulation.py
phyloinfer/dataManipulation.py
phyloinfer/phyloHMC.py
phyloinfer/rateMatrix.py
phyloinfer/refLeapfrog.py
phyloinfer/resultAnalysis.py
phyloinfer/treeManipulation.py
phyloinfer.egg-info/PKG-INFO
phyloinfer.egg-info/SOURCES.txt
phyloinfer.egg-info/dependency_links.txt
phyloinfer.egg-info/not-zip-safe
phyloinfer.egg-info/requires.txt
phyloinfer.egg-info/top_level.txt