Metadata-Version: 1.0
Name: phyloinfer
Version: 0.4
Summary: An efficient Bayesian phylogenetic inference package
Home-page: https://github.com/zcrabbit/PhyloInfer
Author: Cheng Zhang
Author-email: zc.rabbit@gmail.com
License: MIT
Platform: UNKNOWN
